enw/__init__.py
enw/__main__.py
enw/parser.py
enw-0.4.dist-info/DESCRIPTION.rst
enw-0.4.dist-info/METADATA
enw-0.4.dist-info/RECORD
enw-0.4.dist-info/WHEEL
enw-0.4.dist-info/entry_points.txt
enw-0.4.dist-info/metadata.json
enw-0.4.dist-info/top_level.txt
