Metadata-Version: 2.0
Name: enw
Version: 0.4
Summary: Tool for simple administrating of multiple python virtual environment with virtualenv and autoenv.
Home-page: https://github.com/jonathf/enw
Author: Jonathan Feinberg
Author-email: jonathf@gmail.com
License: GPL3
Keywords: virtualenv autoenv configuration
Platform: UNKNOWN
Classifier: Development Status :: 4 - Beta
Classifier: Intended Audience :: Developers
Classifier: Topic :: Software Development :: Build Tools
Classifier: License :: OSI Approved :: GNU General Public License v3 (GPLv3)
Classifier: Programming Language :: Python :: 3.5
Requires-Dist: argcomplete
Requires-Dist: autoenv
Requires-Dist: virtualenv
